fleximod/__init__.py
fleximod/gitinterface.py
fleximod/gitmodules.py
fleximod/lstripreader.py
fleximod/utils.py
fleximod/version.py
fleximod-0.1.7.data/scripts/git-fleximod
fleximod-0.1.7.dist-info/License
fleximod-0.1.7.dist-info/METADATA
fleximod-0.1.7.dist-info/WHEEL
fleximod-0.1.7.dist-info/top_level.txt
fleximod-0.1.7.dist-info/RECORD
