Metadata-Version: 2.1
Name: fleximod
Version: 0.1.7
Summary: Extended support for git-submodule and git-sparse-checkout
Author: Jim Edwards
Maintainer: jedwards4b
License: MIT License
Classifier: Programming Language :: Python :: 3
Classifier: License :: OSI Approved :: MIT License
Classifier: Operating System :: OS Independent
Requires-Python: >=3.6
License-File: License
Requires-Dist: GitPython
